simpletag
