Metadata-Version: 1.1
Name: simpletag
Version: 0.1.3
Summary: Plug-n-Play Simple Tag Library
Home-page: https://pypi.python.org/pypi/simpletag
Author: Acer.Yang
Author-email: yangacer@gmail.com
License: MIT
Platform: UNKNOWN
Classifier: Programming Language :: Python :: 2
Classifier: Intended Audience :: Developers
Classifier: License :: OSI Approved :: MIT License
Classifier: Topic :: Software Development :: Libraries
Classifier: Topic :: Utilities
